inject_environment_variables/__init__.py
inject_environment_variables/decorator.py
inject_environment_variables-1.1.0.dist-info/LICENSE
inject_environment_variables-1.1.0.dist-info/METADATA
inject_environment_variables-1.1.0.dist-info/WHEEL
inject_environment_variables-1.1.0.dist-info/top_level.txt
inject_environment_variables-1.1.0.dist-info/RECORD
