Metadata-Version: 2.2
Name: inject-environment-variables
Version: 1.1.0
Summary: Simple tools for temporatily injecting variables into the environment
Author: Tayler Kemsley
License: MIT License
Project-URL: Homepage, https://github.com/tayler-kemsley/python-inject-environment-variables
Classifier: License :: OSI Approved :: MIT License
Classifier: Programming Language :: Python
Classifier: Programming Language :: Python :: 3
Requires-Python: >=3.9
License-File: LICENSE
Provides-Extra: dev
Requires-Dist: tox; extra == "dev"
Requires-Dist: pytest; extra == "dev"
Requires-Dist: mypy; extra == "dev"
Requires-Dist: flake8; extra == "dev"
